pre5g/__init__.py
pre5g/labelen.py
pre5g/normalization.py
pre5g/nullvalue.py
pre5g/onehoten.py
pre5g/robustscaler.py
pre5g/setup.py
pre5g/standardization.py
pre5g/winsorization.py
pre5g-4.1.dist-info/LICENSE
pre5g-4.1.dist-info/METADATA
pre5g-4.1.dist-info/WHEEL
pre5g-4.1.dist-info/top_level.txt
pre5g-4.1.dist-info/RECORD
