Metadata-Version: 2.1
Name: pre5g
Version: 4.1
Summary: An preprocessing package
Author: SnehaM
Author-email: 1js20cs161@gmail.com
License: MIT
Keywords: example,package
Classifier: License :: OSI Approved :: MIT License
Classifier: Programming Language :: Python :: 3
Classifier: Programming Language :: Python :: 3.9
Classifier: Programming Language :: Python :: 3.8
Classifier: Programming Language :: Python :: 3.7
Classifier: Programming Language :: Python :: 3.6
License-File: LICENSE
